CHANGES.txt
CONTRIBUTORS.txt
MANIFEST.in
README.txt
setup.py
docs/LICENSE.GPL
docs/LICENSE.txt
src/z3c/__init__.py
src/z3c.formwidget.optgroup.egg-info/PKG-INFO
src/z3c.formwidget.optgroup.egg-info/SOURCES.txt
src/z3c.formwidget.optgroup.egg-info/dependency_links.txt
src/z3c.formwidget.optgroup.egg-info/entry_points.txt
src/z3c.formwidget.optgroup.egg-info/namespace_packages.txt
src/z3c.formwidget.optgroup.egg-info/not-zip-safe
src/z3c.formwidget.optgroup.egg-info/requires.txt
src/z3c.formwidget.optgroup.egg-info/top_level.txt
src/z3c/formwidget/__init__.py
src/z3c/formwidget/optgroup/__init__.py
src/z3c/formwidget/optgroup/configure.zcml
src/z3c/formwidget/optgroup/display.pt
src/z3c/formwidget/optgroup/input.pt
src/z3c/formwidget/optgroup/interfaces.py
src/z3c/formwidget/optgroup/widget.py